<?xml version="1.0" encoding="UTF-8"?>
<!--
 *************************************************************************
 * The contents of this file are subject to the Openbravo  Public  License
 * Version  1.1  (the  "License"),  being   the  Mozilla   Public  License
 * Version 1.1  with a permitted attribution clause; you may not  use this
 * file except in compliance with the License. You  may  obtain  a copy of
 * the License at http://www.openbravo.com/legal/license.html 
 * Software distributed under the License  is  distributed  on  an "AS IS"
 * basis, WITHOUT WARRANTY OF ANY KIND, either express or implied. See the
 * License for the specific  language  governing  rights  and  limitations
 * under the License. 
 * The Original Code is Openbravo ERP. 
 * The Initial Developer of the Original Code is Openbravo SLU 
 * All portions are Copyright (C) 2001-2010 Openbravo SLU 
 * All Rights Reserved. 
 * Contributor(s):  ______________________________________.
 ************************************************************************
-->
<REPORT>
	<template file="BusinessPartner.html"/>
	<PARAMETER id="paramCheckClient" name="checkClient" default="customer"/>
	<PARAMETER id="paramCheckVendor" name="checkVendor" default="vendor"/>
	<PARAMETER id="paramCheckAll" name="checkAll" default="all"/>
	<PARAMETER id="paramDirectory" name="directory" default=""/>
	<PARAMETER id="paramLanguage" name="language" default=""/>
	<PARAMETER id="paramCSS" name="theme" attribute="href" replace="Default"/>
	
	<PARAMETER id="paramKey" name="key" attribute="value" replaceCharacters="htmlPreformated"/>
	<PARAMETER id="paramName" name="name" attribute="value" replaceCharacters="htmlPreformated"/>
	<PARAMETER id="fieldClientsSelect" name="clients" boolean="checked" withId="paramCheckClient"/>
	<PARAMETER id="fieldVendorsSelect" name="vendors" boolean="checked" withId="paramCheckVendor"/>
	<PARAMETER id="fieldAllSelect" name="all" boolean="checked" withId="paramCheckAll"/>
	<PARAMETER id="fieldOrgs" name="orgs" replace="xx" attribute="value" />

	<PARAMETER id="grid" name="grid" attribute="numrows" />
	<PARAMETER id="grid" name="grid_Offset" attribute="offset" />
	<PARAMETER id="grid" name="grid_SortCols" attribute="sortcols" />
	<PARAMETER id="grid" name="grid_SortDirs" attribute="sortdirs" />
	<PARAMETER id="grid" name="grid_Default" attribute="defaultrow" />

	<PARAMETER id="jsFocusOnField" name="jsFocusOnField" />
	<DISCARD id="discard"/>
</REPORT>
