<?xml version="1.0"?>
  <database name="TABLE M_PRODUCTPRICE">
    <table name="M_PRODUCTPRICE" primaryKey="M_PRODUCTPRICE_KEY">
      <column name="M_PRODUCTPRICE_ID" primaryKey="true" required="true" type="VARCHAR" size="32" autoIncrement="false">
        <default/>
        <onCreateDefault><![CDATA[get_uuid()]]></onCreateDefault>
      </column>
      <column name="M_PRICELIST_VERSION_ID" primaryKey="false" required="true" type="VARCHAR" size="32" autoIncrement="false">
        <default/>
        <onCreateDefault/>
      </column>
      <column name="M_PRODUCT_ID" primaryKey="false" required="true" type="VARCHAR" size="32" autoIncrement="false">
        <default/>
        <onCreateDefault/>
      </column>
      <column name="AD_CLIENT_ID" primaryKey="false" required="true" type="VARCHAR" size="32" autoIncrement="false">
        <default/>
        <onCreateDefault/>
      </column>
      <column name="AD_ORG_ID" primaryKey="false" required="true" type="VARCHAR" size="32" autoIncrement="false">
        <default/>
        <onCreateDefault/>
      </column>
      <column name="ISACTIVE" primaryKey="false" required="true" type="CHAR" size="1" autoIncrement="false">
        <default><![CDATA[Y]]></default>
        <onCreateDefault/>
      </column>
      <column name="CREATED" primaryKey="false" required="true" type="TIMESTAMP" size="7" autoIncrement="false">
        <default><![CDATA[SYSDATE]]></default>
        <onCreateDefault/>
      </column>
      <column name="CREATEDBY" primaryKey="false" required="true" type="VARCHAR" size="32" autoIncrement="false">
        <default/>
        <onCreateDefault/>
      </column>
      <column name="UPDATED" primaryKey="false" required="true" type="TIMESTAMP" size="7" autoIncrement="false">
        <default><![CDATA[SYSDATE]]></default>
        <onCreateDefault/>
      </column>
      <column name="UPDATEDBY" primaryKey="false" required="true" type="VARCHAR" size="32" autoIncrement="false">
        <default/>
        <onCreateDefault/>
      </column>
      <column name="PRICELIST" primaryKey="false" required="true" type="DECIMAL" autoIncrement="false">
        <default><![CDATA[0]]></default>
        <onCreateDefault/>
      </column>
      <column name="PRICESTD" primaryKey="false" required="true" type="DECIMAL" autoIncrement="false">
        <default><![CDATA[0]]></default>
        <onCreateDefault/>
      </column>
      <column name="PRICELIMIT" primaryKey="false" required="true" type="DECIMAL" autoIncrement="false">
        <default><![CDATA[0]]></default>
        <onCreateDefault/>
      </column>
      <foreign-key foreignTable="AD_CLIENT" name="M_PRODUCTPRICE_AD_CLIENT">
        <reference local="AD_CLIENT_ID" foreign="AD_CLIENT_ID"/>
      </foreign-key>
      <foreign-key foreignTable="AD_ORG" name="M_PRODUCTPRICE_AD_ORG">
        <reference local="AD_ORG_ID" foreign="AD_ORG_ID"/>
      </foreign-key>
      <foreign-key foreignTable="M_PRICELIST_VERSION" name="M_PRODUCTPRICE_M_PRICELIST_VER" onDelete="cascade">
        <reference local="M_PRICELIST_VERSION_ID" foreign="M_PRICELIST_VERSION_ID"/>
      </foreign-key>
      <foreign-key foreignTable="M_PRODUCT" name="M_PRODUCTPRICE_M_PRODUCT" onDelete="cascade">
        <reference local="M_PRODUCT_ID" foreign="M_PRODUCT_ID"/>
      </foreign-key>
      <index name="M_PRODUCTPRICE_PRODUCT" unique="false">
        <index-column name="M_PRODUCT_ID"/>
      </index>
      <unique name="M_PRODUCTPRICE_PRICELIST_VE_UN">
        <unique-column name="M_PRICELIST_VERSION_ID"/>
        <unique-column name="M_PRODUCT_ID"/>
      </unique>
      <check name="M_PRODUCTPRICE_ISACTIVE_CHECK"><![CDATA[ISACTIVE IN ('Y', 'N')]]></check>
    </table>
  </database>
