<?xml version="1.0" encoding="UTF-8"?>
<!--
 *************************************************************************
 * The contents of this file are subject to the Openbravo  Public  License
 * Version  1.1  (the  "License"),  being   the  Mozilla   Public  License
 * Version 1.1  with a permitted attribution clause; you may not  use this
 * file except in compliance with the License. You  may  obtain  a copy of
 * the License at http://www.openbravo.com/legal/license.html 
 * Software distributed under the License  is  distributed  on  an "AS IS"
 * basis, WITHOUT WARRANTY OF ANY KIND, either express or implied. See the
 * License for the specific  language  governing  rights  and  limitations
 * under the License. 
 * The Original Code is Openbravo ERP. 
 * The Initial Developer of the Original Code is Openbravo SLU 
 * All portions are Copyright (C) 2008-2010 Openbravo SLU 
 * All Rights Reserved. 
 * Contributor(s):  ______________________________________.
 ************************************************************************
-->
<REPORT>
  <template file="ModuleTreeDescription.srpt"/>
   <structure name="structureDesc">
    <FIELD id="name">name</FIELD>
    <FIELD id="version">version</FIELD>
    <FIELD id="description">description</FIELD>
    
    <FIELD id="help">help</FIELD>
    <FIELD id="author">author</FIELD>
    <FIELD id="url" attribute="onclick" replace="xx">url</FIELD>
    <FIELD id="url">url</FIELD>
    <FIELD id="status" attribute="onclick">linkclick</FIELD>
    <FIELD id="status">linkname</FIELD>
    
    <FIELD id="updateversion">updateversion</FIELD>
    <FIELD id="updatedescription">updatedescription</FIELD>
    <FIELD id="updatelink" attribute="onclick" replace="xx">updateVerId</FIELD>
    
    <SECTION id="description"/>
  </structure>

  <DISCARD id="discard"/>
</REPORT>
