<?xml version='1.0' encoding='UTF-8'?>
<data>
<!--0--><AD_CLIENT>
<!--0-->  <AD_CLIENT_ID><![CDATA[0]]></AD_CLIENT_ID>
<!--0-->  <AD_ORG_ID><![CDATA[0]]></AD_ORG_ID>
<!--0-->  <ISACTIVE><![CDATA[Y]]></ISACTIVE>
<!--0-->  <VALUE><![CDATA[SYSTEM]]></VALUE>
<!--0-->  <NAME><![CDATA[System]]></NAME>
<!--0-->  <DESCRIPTION><![CDATA[System Client]]></DESCRIPTION>
<!--0-->  <SMTPHOST><![CDATA[localhost]]></SMTPHOST>
<!--0-->  <REQUESTEMAIL><![CDATA[you@company.org]]></REQUESTEMAIL>
<!--0-->  <REQUESTUSER><![CDATA[you]]></REQUESTUSER>
<!--0-->  <REQUESTUSERPW><![CDATA[yourpwd]]></REQUESTUSERPW>
<!--0-->  <REQUESTFOLDER><![CDATA[request]]></REQUESTFOLDER>
<!--0-->  <AD_LANGUAGE><![CDATA[en_US]]></AD_LANGUAGE>
<!--0-->  <ISMULTILINGUALDOCUMENT><![CDATA[Y]]></ISMULTILINGUALDOCUMENT>
<!--0-->  <ISSMTPAUTHORIZATION><![CDATA[N]]></ISSMTPAUTHORIZATION>
<!--0--></AD_CLIENT>

</data>
